rapidcrawl/__init__.py
rapidcrawl/cli.py
rapidcrawl/client.py
rapidcrawl/exceptions.py
rapidcrawl/models.py
rapidcrawl/utils.py
rapidcrawl/features/__init__.py
rapidcrawl/features/crawl.py
rapidcrawl/features/map.py
rapidcrawl/features/scrape.py
rapidcrawl/features/search.py
rapid_crawl-0.1.0.dist-info/METADATA
rapid_crawl-0.1.0.dist-info/WHEEL
rapid_crawl-0.1.0.dist-info/entry_points.txt
rapid_crawl-0.1.0.dist-info/licenses/LICENSE
rapid_crawl-0.1.0.dist-info/RECORD
