Metadata-Version: 2.4
Name: rapid-crawl
Version: 0.1.0
Summary: A powerful Python SDK for web scraping, crawling, and data extraction - inspired by Firecrawl
Project-URL: Homepage, https://github.com/aoneahsan/rapid-crawl
Project-URL: Documentation, https://github.com/aoneahsan/rapid-crawl/blob/main/README.md
Project-URL: Issues, https://github.com/aoneahsan/rapid-crawl/issues
Project-URL: Source, https://github.com/aoneahsan/rapid-crawl
Project-URL: Changelog, https://github.com/aoneahsan/rapid-crawl/blob/main/CHANGELOG.md
Project-URL: Funding, https://github.com/sponsors/aoneahsan
Project-URL: Twitter, https://twitter.com/aoneahsan
Author-email: Ahsan Mahmood <aoneahsan@gmail.com>
Maintainer-email: Ahsan Mahmood <aoneahsan@gmail.com>
License: MIT
License-File: LICENSE
Keywords: ai,content-extraction,crawling,data-extraction,data-mining,html-to-markdown,llm,markdown,scraper,spider,web-automation,web-crawler,web-scraping,website-crawler
Classifier: Development Status :: 3 - Alpha
Classifier: Framework :: AsyncIO
Classifier: Intended Audience :: Developers
Classifier: Intended Audience :: Information Technology
Classifier: Intended Audience :: Science/Research
Classifier: License :: OSI Approved :: MIT License
Classifier: Natural Language :: English
Classifier: Operating System :: OS Independent
Classifier: Programming Language :: Python :: 3
Classifier: Programming Language :: Python :: 3.8
Classifier: Programming Language :: Python :: 3.9
Classifier: Programming Language :: Python :: 3.10
Classifier: Programming Language :: Python :: 3.11
Classifier: Programming Language :: Python :: 3.12
Classifier: Programming Language :: Python :: Implementation :: CPython
Classifier: Topic :: Internet :: WWW/HTTP
Classifier: Topic :: Internet :: WWW/HTTP :: Dynamic Content
Classifier: Topic :: Internet :: WWW/HTTP :: Indexing/Search
Classifier: Topic :: Scientific/Engineering :: Information Analysis
Classifier: Topic :: Software Development :: Libraries
Classifier: Topic :: Software Development :: Libraries :: Python Modules
Classifier: Topic :: Text Processing :: Markup :: HTML
Classifier: Topic :: Text Processing :: Markup :: Markdown
Classifier: Typing :: Typed
Requires-Python: >=3.8
Requires-Dist: aiofiles>=23.2.0
Requires-Dist: beautifulsoup4>=4.12.0
Requires-Dist: click>=8.1.0
Requires-Dist: html2text>=2024.2.26
Requires-Dist: httpx>=0.27.0
Requires-Dist: lxml>=5.0.0
Requires-Dist: markdownify>=0.11.6
Requires-Dist: pillow>=10.0.0
Requires-Dist: playwright>=1.40.0
Requires-Dist: pydantic>=2.0.0
Requires-Dist: pypdf2>=3.0.0
Requires-Dist: python-dotenv>=1.0.0
Requires-Dist: python-magic>=0.4.27
Requires-Dist: rich>=13.7.0
Requires-Dist: tenacity>=8.2.0
Provides-Extra: dev
Requires-Dist: black>=24.0.0; extra == 'dev'
Requires-Dist: httpx[http2]; extra == 'dev'
Requires-Dist: mypy>=1.8.0; extra == 'dev'
Requires-Dist: pre-commit>=3.6.0; extra == 'dev'
Requires-Dist: pytest-asyncio>=0.23.0; extra == 'dev'
Requires-Dist: pytest-cov>=4.1.0; extra == 'dev'
Requires-Dist: pytest-mock>=3.12.0; extra == 'dev'
Requires-Dist: pytest>=8.0.0; extra == 'dev'
Requires-Dist: ruff>=0.3.0; extra == 'dev'
Requires-Dist: types-beautifulsoup4; extra == 'dev'
Requires-Dist: types-requests; extra == 'dev'
